fastack_celery/__init__.py
fastack_celery/globals.py
fastack_celery-0.1.0.dist-info/WHEEL
fastack_celery-0.1.0.dist-info/METADATA
fastack_celery-0.1.0.dist-info/RECORD
