Metadata-Version: 2.1
Name: fastack-celery
Version: 0.1.0
Summary: Celery Integration For Fastack
Home-page: https://github.com/fastack-dev/fastack-celery
License: MIT
Author: aprilahijriyan
Author-email: hijriyan23@gmail.com
Maintainer: aprilahijriyan
Maintainer-email: 37798612+aprilahijriyan@users.noreply.github.com
Requires-Python: >=3.7
Classifier: Development Status :: 4 - Beta
Classifier: Environment :: Web Environment
Classifier: Intended Audience :: Developers
Classifier: Intended Audience :: Information Technology
Classifier: Intended Audience :: System Administrators
Classifier: License :: OSI Approved :: MIT License
Classifier: Operating System :: OS Independent
Classifier: Programming Language :: Python
Classifier: Programming Language :: Python :: 3
Classifier: Programming Language :: Python :: 3 :: Only
Classifier: Programming Language :: Python :: 3.10
Classifier: Programming Language :: Python :: 3.7
Classifier: Programming Language :: Python :: 3.8
Classifier: Programming Language :: Python :: 3.9
Classifier: Topic :: Internet
Classifier: Topic :: Software Development
Classifier: Topic :: Software Development :: Libraries
Classifier: Topic :: Software Development :: Libraries :: Application Frameworks
Classifier: Topic :: Software Development :: Libraries :: Python Modules
Requires-Dist: celery (>=5.2.3,<6.0.0)
Requires-Dist: fastack (>=4.0.0,<5.0.0)
Project-URL: Bug Tracker, https://github.com/fastack-dev/fastack-celery/issues
Project-URL: Repository, https://github.com/fastack-dev/fastack-celery
